reverse_geocoder_whl.cpython-311-x86_64-linux-musl.so
reverse_geocoder_whl/__init__.py
reverse_geocoder_whl/cKDTree_MP.py
reverse_geocoder_whl/rg_cities1000.csv
reverse_geocoder_whl.libs/libgcc_s-2298274a.so.1
reverse_geocoder_whl.libs/libstdc++-08d5c7eb.so.6.0.33
reverse_geocoder_whl-1.6.dist-info/METADATA
reverse_geocoder_whl-1.6.dist-info/WHEEL
reverse_geocoder_whl-1.6.dist-info/top_level.txt
reverse_geocoder_whl-1.6.dist-info/RECORD
reverse_geocoder_whl-1.6.dist-info/licenses/LICENSE
