Metadata-Version: 2.4
Name: reverse_geocoder_whl
Version: 1.6
Summary: Fast, offline reverse geocoder
Home-page: https://github.com/TalAmuyal/reverse-geocoder-whl
Author-email: Ajay Thampi <ajay.thampi@gmail.com>
Requires-Python: >=3.10
License-File: LICENSE
Requires-Dist: numpy>=1.11.0
Requires-Dist: scipy<1.11,>=0.17.1
Dynamic: home-page
Dynamic: license-file
